artificer/conversations/__init__.py
artificer/conversations/models.py
artificer/conversations/module.py
artificer/conversations/step.py
artificer/conversations/storage.py
artificer_conversations-0.1.0.dist-info/METADATA
artificer_conversations-0.1.0.dist-info/WHEEL
artificer_conversations-0.1.0.dist-info/RECORD
