Metadata-Version: 2.4
Name: artificer-conversations
Version: 0.1.0
Summary: Queue-based conversation system for Artificer workflows
Requires-Python: >=3.10
Requires-Dist: artificer-cli>=0.1.0a2
Requires-Dist: pydantic>=2.0
Provides-Extra: workflows
Requires-Dist: artificer-workflows>=0.1.0a9; extra == 'workflows'
